{
  "mon": [
    {
      "begin": "9:30",
      "end": "10:50",
      "week": 1,
      "place": "403 Кронверкский пр., д. 49, лит. А",
      "subj": "Экология(Лек)",
      "lect": "Копилевич Юрий Исаакович"
    },
    {
      "begin": "11:00",
      "end": "12:20",
      "week": 1,
      "place": "429 Кронверкский пр., д. 49, лит. А",
      "subj": "Экология(Прак)",
      "lect": "Копилевич Юрий Исаакович"
    },
    {
      "begin": "12:40",
      "end": "14:00",
      "week": 0,
      "place": "Электроприбор",
      "subj": "Технологии обработки конструкционных материалов(Лек)",
      "lect": "Пешехонов Владимир Григорьевич"
    },
    {
      "begin": "14:20",
      "end": "15:40",
      "week": 1,
      "place": "Электроприбор",
      "subj": "Технологии обработки конструкционных материалов(Лаб)",
      "lect": "Пешехонов Владимир Григорьевич"
    },
    {
      "begin": "14:20",
      "end": "15:40",
      "week": 2,
      "place": "Электроприбор",
      "subj": "Технологии обработки конструкционных материалов(Прак)",
      "lect": "Пешехонов Владимир Григорьевич"
    }
  ],
  "tue": [
    {
      "begin": "9:30",
      "end": "10:50",
      "week": 2,
      "place": "322 Кронверкский пр., д. 49, лит. А",
      "subj": "Организация и управление бизнес-процессами(Лек)",
      "lect": "Королева Лада Александровна"
    },
    {
      "begin": "9:30",
      "end": "10:50",
      "week": 1,
      "place": "422 Кронверкский пр., д. 49, лит. А",
      "subj": "Социально-политические проблемы современного общества(Лек)",
      "lect": "Борисов Олег Сергеевич"
    },
    {
      "begin": "11:00",
      "end": "12:20",
      "week": 1,
      "place": "426 Кронверкский пр., д. 49, лит. А",
      "subj": "Организация и управление бизнес-процессами(Прак)",
      "lect": "Королева Лада Александровна"
    },
    {
      "begin": "11:00",
      "end": "12:20",
      "week": 2,
      "place": "427 Кронверкский пр., д. 49, лит. А",
      "subj": "Социально-политические проблемы современного общества(Прак)",
      "lect": "Борисов Олег Сергеевич"
    },
    {
      "begin": "12:40",
      "end": "14:00",
      "week": 1,
      "place": "409 Кронверкский пр., д. 49, лит. А",
      "subj": "Организация и управление бизнес-процессами(Прак)",
      "lect": "Королева Лада Александровна"
    },
    {
      "begin": "12:40",
      "end": "14:00",
      "week": 2,
      "place": "427 Кронверкский пр., д. 49, лит. А",
      "subj": "Социально-политические проблемы современного общества(Прак)",
      "lect": "Борисов Олег Сергеевич"
    }
  ],
  "wed": [
    {
      "begin": "8:00",
      "end": "9:20",
      "week": 0,
      "place": "пер.Вяземский, д.5-7, лит. А",
      "subj": "Физическая культура(Прак)",
      "lect": ""
    },
    {
      "begin": "11:00",
      "end": "12:20",
      "week": 1,
      "place": "ул.Чайковского, д.11/2, лит. А",
      "subj": "Иностранный язык(Прак)",
      "lect": ""
    },
    {
      "begin": "11:00",
      "end": "12:20",
      "week": 2,
      "place": "Электроприбор",
      "subj": "Электроника и микропроцессорная техника(Лаб)",
      "lect": "Аксененко Виктор Дмитриевич"
    },
    {
      "begin": "12:40",
      "end": "14:00",
      "week": 2,
      "place": "Электроприбор",
      "subj": "Электроника и микропроцессорная техника(Лаб)",
      "lect": "Аксененко Виктор Дмитриевич"
    }
  ],
  "thu": [
    {
      "begin": "9:30",
      "end": "10:50",
      "week": 2,
      "place": "Электроприбор",
      "subj": "Теория вероятностей и математическая статистика(Лек)",
      "lect": "Степанов Олег Андреевич"
    },
    {
      "begin": "11:00",
      "end": "12:20",
      "week": 1,
      "place": "475 Кронверкский пр., д. 49, лит. А",
      "subj": "Дополнительные главы физики(Прак)",
      "lect": "Башнина Галина Львовна"
    },
    {
      "begin": "11:00",
      "end": "12:20",
      "week": 2,
      "place": "Электроприбор",
      "subj": "Теория вероятностей и математическая статистика(Прак)",
      "lect": "Степанов Олег Андреевич"
    },
    {
      "begin": "12:40",
      "end": "14:00",
      "week": 2,
      "place": "Электроприбор",
      "subj": "Электроника и микропроцессорная техника(Лек)",
      "lect": ""
    },
    {
      "begin": "12:40",
      "end": "14:00",
      "week": 1,
      "place": "475 Кронверкский пр., д. 49, лит. А",
      "subj": "Дополнительные главы физики(Прак)",
      "lect": "Башнина Галина Львовна"
    },
    {
      "begin": "14:20",
      "end": "15:40",
      "week": 2,
      "place": "Электроприбор",
      "subj": "Электроника и микропроцессорная техника(Лаб)",
      "lect": ""
    }
  ],
  "fri": [
    {
      "begin": "9:30",
      "end": "10:50",
      "week": 0,
      "place": "403 Кронверкский пр., д. 49, лит. А",
      "subj": "Дополнительные главы физики(Лек)",
      "lect": "Боярский Кирилл Кириллович"
    },
    {
      "begin": "11:00",
      "end": "12:20",
      "week": 0,
      "place": "Электроприбор",
      "subj": "Теория колебаний(Прак)",
      "lect": "Лопарев Алексей Валерьевич"
    },
    {
      "begin": "12:40",
      "end": "14:00",
      "week": 1,
      "place": "Электроприбор",
      "subj": "Теория колебаний(Прак)",
      "lect": "Лопарев Алексей Валерьевич"
    }
  ]
}
