{
  "mon": [
    {
      "begin": "9:30",
      "end": "10:50",
      "week": 1,
      "place": "ул.Ломоносова, д.9, лит.В",
      "subj": "Физическая культура(Прак) :  с 1-9 нед.",
      "lect": ""
    },
    {
      "begin": "9:30",
      "end": "10:50",
      "week": 2,
      "place": "ул.Ломоносова, д.9, лит.В",
      "subj": "Физическая культура(Прак)",
      "lect": ""
    },
    {
      "begin": "11:00",
      "end": "12:20",
      "week": 0,
      "place": "1124 ул.Ломоносова, д.9, лит.М",
      "subj": "Математика(Прак)",
      "lect": "Камоцкий Владимир Ильич"
    },
    {
      "begin": "13:00",
      "end": "14:20",
      "week": 1,
      "place": "1124 ул.Ломоносова, д.9, лит.М",
      "subj": "Математика(Прак)",
      "lect": "Камоцкий Владимир Ильич"
    },
    {
      "begin": "13:00",
      "end": "14:20",
      "week": 2,
      "place": "2534 ул.Ломоносова, д.9, лит.А",
      "subj": "Введение в специальность(Лек)",
      "lect": "Ишевский Александр Леонидович"
    },
    {
      "begin": "14:30",
      "end": "15:20",
      "week": 1,
      "place": "2534 ул.Ломоносова, д.9, лит.А",
      "subj": "Введение в специальность(Лек)",
      "lect": "Ишевский Александр Леонидович"
    },
    {
      "begin": "14:30",
      "end": "15:20",
      "week": 2,
      "place": "2534 ул.Ломоносова, д.9, лит.А",
      "subj": "Введение в специальность(Прак)",
      "lect": "Ишевский Александр Леонидович"
    }
  ],
  "tue": [
    {
      "begin": "11:00",
      "end": "12:20",
      "week": 0,
      "place": "ул.Ломоносова, д.9, лит.Е",
      "subj": "Иностранный язык(Прак) : кафедра",
      "lect": "Назарова Елена Владимировна"
    },
    {
      "begin": "13:00",
      "end": "14:20",
      "week": 0,
      "place": "1222 ул.Ломоносова, д.9, лит.М",
      "subj": "Математика(Лек)",
      "lect": "Камоцкий Владимир Ильич"
    }
  ],
  "wed": [
    {
      "begin": "9:30",
      "end": "10:50",
      "week": 1,
      "place": "2415 ул.Ломоносова, д.9, лит.А",
      "subj": "Физика(Прак)",
      "lect": "Частый Виктор Леонидович"
    },
    {
      "begin": "11:00",
      "end": "12:20",
      "week": 2,
      "place": "ул.Ломоносова, д.9, лит.Е",
      "subj": "Иностранный язык(Прак) : кафедра",
      "lect": "Назарова Елена Владимировна"
    },
    {
      "begin": "11:00",
      "end": "12:20",
      "week": 1,
      "place": "1122 ул.Ломоносова, д.9, лит.М",
      "subj": "Культурология(Прак)",
      "lect": "Кузнецов Валерий Иванович"
    },
    {
      "begin": "13:00",
      "end": "14:20",
      "week": 1,
      "place": "2530 ул.Ломоносова, д.9, лит.А",
      "subj": "Культурология(Лек)",
      "lect": "Кузнецов Валерий Иванович"
    },
    {
      "begin": "13:00",
      "end": "14:20",
      "week": 2,
      "place": "2534 ул.Ломоносова, д.9, лит.А",
      "subj": "Основы технологии пищевых продуктов(Лек)",
      "lect": "Ишевский Александр Леонидович"
    },
    {
      "begin": "14:30",
      "end": "15:20",
      "week": 0,
      "place": "2321 ул.Ломоносова, д.9, лит.А",
      "subj": "Неорганическая химия(Лек)",
      "lect": "Кириллов Вадим Васильевич"
    }
  ],
  "thu": [
    {
      "begin": "9:30",
      "end": "10:50",
      "week": 1,
      "place": "2305 ул.Ломоносова, д.9, лит.А",
      "subj": "Основы технологии пищевых продуктов(Лаб) :  с 10 нед.",
      "lect": "Бурова Татьяна Евгеньевна"
    },
    {
      "begin": "11:00",
      "end": "12:20",
      "week": 2,
      "place": "2415 ул.Ломоносова, д.9, лит.А",
      "subj": "Физика(Прак)",
      "lect": "Частый Виктор Леонидович"
    },
    {
      "begin": "11:00",
      "end": "12:20",
      "week": 1,
      "place": "2305 ул.Ломоносова, д.9, лит.А",
      "subj": "Основы технологии пищевых продуктов(Лаб) :  с 10 нед.",
      "lect": "Бурова Татьяна Евгеньевна"
    },
    {
      "begin": "13:00",
      "end": "14:20",
      "week": 0,
      "place": "ул.Ломоносова, д.9, лит.В",
      "subj": "Физическая культура(Прак)",
      "lect": ""
    },
    {
      "begin": "14:30",
      "end": "15:20",
      "week": 0,
      "place": "2318 ул.Ломоносова, д.9, лит.А",
      "subj": "Неорганическая химия(Лаб)",
      "lect": "Белкина Елена Ильинична"
    }
  ],
  "fri": [
    {
      "begin": "9:30",
      "end": "10:50",
      "week": 2,
      "place": "1124 ул.Ломоносова, д.9, лит.М",
      "subj": "Основы технологии пищевых продуктов(Прак)",
      "lect": "Бурова Татьяна Евгеньевна"
    },
    {
      "begin": "11:00",
      "end": "12:20",
      "week": 2,
      "place": "1124 ул.Ломоносова, д.9, лит.М",
      "subj": "Основы технологии пищевых продуктов(Прак)",
      "lect": "Бурова Татьяна Евгеньевна"
    },
    {
      "begin": "11:00",
      "end": "12:20",
      "week": 1,
      "place": "1124 ул.Ломоносова, д.9, лит.М",
      "subj": "История(Прак)",
      "lect": "Копанева Елена Михайловна"
    },
    {
      "begin": "13:00",
      "end": "14:20",
      "week": 0,
      "place": "2432 ул.Ломоносова, д.9, лит.А",
      "subj": "Физика(Лек)",
      "lect": "Частый Виктор Леонидович"
    },
    {
      "begin": "14:30",
      "end": "15:20",
      "week": 1,
      "place": "2530 ул.Ломоносова, д.9, лит.А",
      "subj": "История(Лек)",
      "lect": "Копанева Елена Михайловна"
    }
  ]
}
