{
  "mon": [
    {
      "begin": "11:00",
      "end": "12:20",
      "week": 0,
      "place": "ул.Ломоносова, д.9, лит.В",
      "subj": "Физическая культура(Прак)",
      "lect": "Муратова Наталия Викторовна"
    },
    {
      "begin": "11:00",
      "end": "12:20",
      "week": 0,
      "place": "ул.Ломоносова, д.9, лит.В",
      "subj": "Физическая культура(Прак) :  с 1-9 нед.",
      "lect": "Муратова Наталия Викторовна"
    },
    {
      "begin": "13:00",
      "end": "14:20",
      "week": 2,
      "place": "2534 ул.Ломоносова, д.9, лит.А",
      "subj": "Математика(Прак)",
      "lect": "Кудрявцева Ирина Владимировна"
    },
    {
      "begin": "13:00",
      "end": "14:20",
      "week": 1,
      "place": "2515 ул.Ломоносова, д.9, лит.А",
      "subj": "Мировые информационные ресурсы(Лек)",
      "lect": "Селина Елена Георгиевна"
    },
    {
      "begin": "14:30",
      "end": "15:20",
      "week": 1,
      "place": "1220 ул.Ломоносова, д.9, лит.М",
      "subj": "Введение в специальность(Лек)",
      "lect": "Забодалова Людмила Александровна"
    }
  ],
  "tue": [
    {
      "begin": "9:30",
      "end": "10:50",
      "week": 0,
      "place": "2318 ул.Ломоносова, д.9, лит.А",
      "subj": "Неорганическая химия(Лаб)",
      "lect": "Белкина Елена Ильинична"
    },
    {
      "begin": "11:00",
      "end": "12:20",
      "week": 0,
      "place": "ул.Ломоносова, д.9, лит.Е",
      "subj": "Иностранный язык(Прак) : кафедра",
      "lect": "Игнатович Валерий Борисович"
    },
    {
      "begin": "13:00",
      "end": "14:20",
      "week": 0,
      "place": "1222 ул.Ломоносова, д.9, лит.М",
      "subj": "Математика(Лек)",
      "lect": "Камоцкий Владимир Ильич"
    }
  ],
  "wed": [
    {
      "begin": "9:30",
      "end": "10:50",
      "week": 2,
      "place": "2415 ул.Ломоносова, д.9, лит.А",
      "subj": "Физика(Прак)",
      "lect": "Частый Виктор Леонидович"
    },
    {
      "begin": "9:30",
      "end": "10:50",
      "week": 1,
      "place": "1123 ул.Ломоносова, д.9, лит.М",
      "subj": "Математика(Прак)",
      "lect": "Кудрявцева Ирина Владимировна"
    },
    {
      "begin": "11:00",
      "end": "12:20",
      "week": 2,
      "place": "ул.Ломоносова, д.9, лит.Е",
      "subj": "Иностранный язык(Прак) : кафедра",
      "lect": "Игнатович Валерий Борисович"
    },
    {
      "begin": "11:00",
      "end": "12:20",
      "week": 1,
      "place": "1123 ул.Ломоносова, д.9, лит.М",
      "subj": "Математика(Прак)",
      "lect": "Кудрявцева Ирина Владимировна"
    },
    {
      "begin": "13:00",
      "end": "14:20",
      "week": 2,
      "place": "2532 ул.Ломоносова, д.9, лит.А",
      "subj": "Культурология(Прак)",
      "lect": "Кузнецов Валерий Иванович"
    },
    {
      "begin": "13:00",
      "end": "14:20",
      "week": 1,
      "place": "2530 ул.Ломоносова, д.9, лит.А",
      "subj": "Культурология(Лек)",
      "lect": "Кузнецов Валерий Иванович"
    },
    {
      "begin": "14:30",
      "end": "15:20",
      "week": 0,
      "place": "2321 ул.Ломоносова, д.9, лит.А",
      "subj": "Неорганическая химия(Лек)",
      "lect": "Кириллов Вадим Васильевич"
    }
  ],
  "thu": [
    {
      "begin": "9:30",
      "end": "10:50",
      "week": 1,
      "place": "1220 ул.Ломоносова, д.9, лит.М",
      "subj": "Введение в специальность(Прак)",
      "lect": "Забодалова Людмила Александровна"
    },
    {
      "begin": "11:00",
      "end": "12:20",
      "week": 1,
      "place": "2415 ул.Ломоносова, д.9, лит.А",
      "subj": "Физика(Прак)",
      "lect": "Частый Виктор Леонидович"
    },
    {
      "begin": "13:00",
      "end": "14:20",
      "week": 0,
      "place": "ул.Ломоносова, д.9, лит.Е",
      "subj": "Физическая культура(Прак)",
      "lect": "Муратова Наталия Викторовна"
    },
    {
      "begin": "14:30",
      "end": "15:20",
      "week": 0,
      "place": "1220 ул.Ломоносова, д.9, лит.М",
      "subj": "Введение в специальность(Лек) : по 2 нед. ауд.3412",
      "lect": "Забодалова Людмила Александровна"
    }
  ],
  "fri": [
    {
      "begin": "9:30",
      "end": "10:50",
      "week": 1,
      "place": "3310 ул.Ломоносова, д.9, лит.Е",
      "subj": "Мировые информационные ресурсы(Лаб)",
      "lect": "Селина Елена Георгиевна"
    },
    {
      "begin": "11:00",
      "end": "12:20",
      "week": 0,
      "place": "3310 ул.Ломоносова, д.9, лит.Е",
      "subj": "Мировые информационные ресурсы(Лаб)",
      "lect": "Селина Елена Георгиевна"
    },
    {
      "begin": "13:00",
      "end": "14:20",
      "week": 0,
      "place": "2432 ул.Ломоносова, д.9, лит.А",
      "subj": "Физика(Лек)",
      "lect": "Частый Виктор Леонидович"
    },
    {
      "begin": "14:30",
      "end": "15:20",
      "week": 2,
      "place": "2534 ул.Ломоносова, д.9, лит.А",
      "subj": "История(Прак)",
      "lect": "Копанева Елена Михайловна"
    },
    {
      "begin": "14:30",
      "end": "15:20",
      "week": 1,
      "place": "2530 ул.Ломоносова, д.9, лит.А",
      "subj": "История(Лек)",
      "lect": "Копанева Елена Михайловна"
    }
  ]
}
