{
  "mon": [
    {
      "begin": "14:30",
      "end": "15:20",
      "week": 0,
      "place": "4119 ул.Ломоносова, д.9, лит.В",
      "subj": "Промышленная санитария мясной и молочной промышленности(Лек) : лек.+лаб.",
      "lect": "Байченко Анна Алексеевна"
    },
    {
      "begin": "16:00",
      "end": "17:20",
      "week": 0,
      "place": "4119 ул.Ломоносова, д.9, лит.В",
      "subj": "Промышленная санитария мясной и молочной промышленности(Прак) : лаб.+пр.",
      "lect": "Байченко Анна Алексеевна"
    }
  ],
  "tue": [
    {
      "begin": "9:30",
      "end": "10:50",
      "week": 2,
      "place": "ул.Ломоносова, д.9, лит.В",
      "subj": "Анализ технического уровня оборудования мясной и молочной промышленности(Лаб) :  с 1-9 нед., кафедра",
      "lect": "Рогов Борис Аркадьевич"
    },
    {
      "begin": "9:30",
      "end": "10:50",
      "week": 1,
      "place": "ул.Ломоносова, д.9, лит.В",
      "subj": "Анализ технического уровня оборудования мясной и молочной промышленности(Лаб) : кафедра",
      "lect": "Рогов Борис Аркадьевич"
    },
    {
      "begin": "11:00",
      "end": "12:20",
      "week": 0,
      "place": "4505 ул.Ломоносова, д.9, лит.В",
      "subj": "Анализ технического уровня оборудования мясной и молочной промышленности(Лек) : лек.+пр. (по 1 нед. кафедра)",
      "lect": "Рогов Борис Аркадьевич"
    },
    {
      "begin": "13:00",
      "end": "14:20",
      "week": 1,
      "place": "4119 ул.Ломоносова, д.9, лит.В",
      "subj": "Промышленная санитария мясной и молочной промышленности(Прак) :  с 1-9 нед.",
      "lect": "Байченко Анна Алексеевна"
    },
    {
      "begin": "13:00",
      "end": "14:20",
      "week": 2,
      "place": "ул.Ломоносова, д.9, лит.В",
      "subj": "Анализ технического уровня оборудования мясной и молочной промышленности(Прак) : кафедра",
      "lect": "Рогов Борис Аркадьевич"
    }
  ],
  "wed": [
    {
      "begin": "13:00",
      "end": "14:20",
      "week": 1,
      "place": "3401 ул.Ломоносова, д.9, лит.Е",
      "subj": "Менеджмент и маркетинг(Лек)",
      "lect": "Беляев Сергей Иванович"
    },
    {
      "begin": "14:30",
      "end": "15:20",
      "week": 1,
      "place": "4504 ул.Ломоносова, д.9, лит.В",
      "subj": "Защита интеллектуальной собственности(Лек)",
      "lect": "Алексеев Геннадий Валентинович"
    },
    {
      "begin": "14:30",
      "end": "15:20",
      "week": 2,
      "place": "2206 ул.Ломоносова, д.9, лит.А",
      "subj": "Новые конструкционные материалы(Лек) : лек.+пр. с 10нед. ауд. 3327",
      "lect": ""
    },
    {
      "begin": "16:00",
      "end": "17:20",
      "week": 2,
      "place": "2206 ул.Ломоносова, д.9, лит.А",
      "subj": "Новые конструкционные материалы(Прак) : Ермаков Б.С.",
      "lect": ""
    }
  ],
  "fri": [
    {
      "begin": "11:00",
      "end": "12:20",
      "week": 1,
      "place": "3401 ул.Ломоносова, д.9, лит.Е",
      "subj": "Менеджмент и маркетинг(Лаб)",
      "lect": "Беляев Сергей Иванович"
    },
    {
      "begin": "13:00",
      "end": "14:20",
      "week": 0,
      "place": "4101 ул.Ломоносова, д.9, лит.В",
      "subj": "Защита интеллектуальной собственности(Прак)",
      "lect": "Алексеев Геннадий Валентинович"
    },
    {
      "begin": "14:30",
      "end": "15:20",
      "week": 2,
      "place": "3401 ул.Ломоносова, д.9, лит.Е",
      "subj": "Менеджмент и маркетинг(Прак)",
      "lect": "Беляев Сергей Иванович"
    },
    {
      "begin": "16:00",
      "end": "17:20",
      "week": 2,
      "place": "3401 ул.Ломоносова, д.9, лит.Е",
      "subj": "Менеджмент и маркетинг(Прак)",
      "lect": "Беляев Сергей Иванович"
    }
  ]
}
