{
  "mon": [
    {
      "begin": "14:30",
      "end": "",
      "week": 0,
      "place": "ул.Ломоносова, д.9, лит.Е",
      "subj": "Бизнес-планирование в отрасли(Лек)лек.+пр. (каб. Экон.)",
      "lect": "Минко Игорь Степанович"
    },
    {
      "begin": "16:00",
      "end": "",
      "week": 0,
      "place": "ул.Ломоносова, д.9, лит.Е",
      "subj": "Бизнес-планирование в отрасли(Прак)каб.экономики",
      "lect": "Минко Игорь Степанович"
    }
  ],
  "tue": [
    {
      "begin": "16:00",
      "end": "",
      "week": 0,
      "place": "2515 ул.Ломоносова, д.9, лит.А",
      "subj": "Венчурное финансирование(Прак)",
      "lect": "Василенок Виктор Леонидович"
    }
  ],
  "wed": [
    {
      "begin": "09:30",
      "end": "",
      "week": 0,
      "place": "3401 ул.Ломоносова, д.9, лит.Е",
      "subj": "Управление инновационным развитием организации(Прак)",
      "lect": "Шамина Любовь Константиновна"
    },
    {
      "begin": "11:00",
      "end": "",
      "week": 1,
      "place": "1611 ул.Ломоносова, д.9, лит.М",
      "subj": "Методы экспертных оценок в управлении(Лек)",
      "lect": "Шапиро Наталья Александровна"
    },
    {
      "begin": "11:00",
      "end": "",
      "week": 2,
      "place": "3401 ул.Ломоносова, д.9, лит.Е",
      "subj": "Управление инновационным развитием организации(Прак)",
      "lect": "Шамина Любовь Константиновна"
    },
    {
      "begin": "13:00",
      "end": "",
      "week": 0,
      "place": "1611 ул.Ломоносова, д.9, лит.М",
      "subj": "Методы экспертных оценок в управлении(Прак)",
      "lect": "Шапиро Наталья Александровна"
    }
  ],
  "thu": [
    {
      "begin": "11:00",
      "end": "",
      "week": 2,
      "place": "1611 ул.Ломоносова, д.9, лит.М",
      "subj": "Венчурное финансирование(Лек)",
      "lect": "Василенок Виктор Леонидович"
    },
    {
      "begin": "13:00",
      "end": "",
      "week": 0,
      "place": "ул.Ломоносова, д.9, лит.Е",
      "subj": "Иностранный язык для академических и специальных целей(Прак)кафедра",
      "lect": ""
    },
    {
      "begin": "14:30",
      "end": "",
      "week": 0,
      "place": "3104 ул.Ломоносова, д.9, лит.Е",
      "subj": "Управление персоналом(Прак)",
      "lect": "Минченко Лидия Викторовна"
    },
    {
      "begin": "16:00",
      "end": "",
      "week": 1,
      "place": "3104 ул.Ломоносова, д.9, лит.Е",
      "subj": "Управление персоналом(Прак)",
      "lect": "Минченко Лидия Викторовна"
    }
  ]
}
