{
  "mon": [
    {
      "begin": "14:30",
      "end": "15:20",
      "week": 0,
      "place": "1122 ул.Ломоносова, д.9, лит.М",
      "subj": "Экологический аудит(Лек) : лек.+пр.",
      "lect": "Дидиков Александр Евгеньевич"
    },
    {
      "begin": "16:00",
      "end": "17:20",
      "week": 0,
      "place": "1122а ул.Ломоносова, д.9, лит.М",
      "subj": "Экологический аудит(Лаб)",
      "lect": "Дидиков Александр Евгеньевич"
    },
    {
      "begin": "17:30",
      "end": "18:50",
      "week": 1,
      "place": "1122а ул.Ломоносова, д.9, лит.М",
      "subj": "Экологический аудит(Лаб) :  с 1-9 нед.",
      "lect": "Дидиков Александр Евгеньевич"
    }
  ],
  "wed": [
    {
      "begin": "11:00",
      "end": "12:20",
      "week": 1,
      "place": "1122а ул.Ломоносова, д.9, лит.М",
      "subj": "Экологический дизайн и оценка жизненного цикла(Лаб) :  с 1-9 нед.",
      "lect": "Копыльцова Светлана Евгеньевна"
    },
    {
      "begin": "13:00",
      "end": "14:20",
      "week": 0,
      "place": "1122а ул.Ломоносова, д.9, лит.М",
      "subj": "Экологический дизайн и оценка жизненного цикла(Лаб) : по 2 нед. ауд.2407",
      "lect": "Копыльцова Светлана Евгеньевна"
    },
    {
      "begin": "14:30",
      "end": "15:20",
      "week": 0,
      "place": "3412 ул.Ломоносова, д.9, лит.Е",
      "subj": "Экологический дизайн и оценка жизненного цикла(Лек) : лек.+пр.",
      "lect": "Копыльцова Светлана Евгеньевна"
    }
  ],
  "thu": [
    {
      "begin": "14:30",
      "end": "15:20",
      "week": 2,
      "place": "2406 ул.Ломоносова, д.9, лит.А",
      "subj": "Наилучшие доступные технологии в производстве(Лек) : лек.+пр.",
      "lect": "Сергиенко Ольга Ивановна"
    },
    {
      "begin": "16:00",
      "end": "17:20",
      "week": 0,
      "place": "2406 ул.Ломоносова, д.9, лит.А",
      "subj": "Наилучшие доступные технологии в производстве(Лаб)",
      "lect": "Сергиенко Ольга Ивановна"
    },
    {
      "begin": "17:30",
      "end": "18:50",
      "week": 1,
      "place": "2406 ул.Ломоносова, д.9, лит.А",
      "subj": "Наилучшие доступные технологии в производстве(Прак)",
      "lect": "Сергиенко Ольга Ивановна"
    },
    {
      "begin": "17:30",
      "end": "18:50",
      "week": 2,
      "place": "2406 ул.Ломоносова, д.9, лит.А",
      "subj": "Наилучшие доступные технологии в производстве(Прак) :  с 1-9 нед.",
      "lect": "Сергиенко Ольга Ивановна"
    }
  ],
  "fri": [
    {
      "begin": "14:30",
      "end": "15:20",
      "week": 0,
      "place": "2115 ул.Ломоносова, д.9, лит.А",
      "subj": "Экологические риски и экологическое страхование(Лек) : лек.+пр.",
      "lect": "Сергиенко Ольга Ивановна"
    },
    {
      "begin": "16:00",
      "end": "17:20",
      "week": 0,
      "place": "2115 ул.Ломоносова, д.9, лит.А",
      "subj": "Экологические риски и экологическое страхование(Прак) : лаб.+пр.",
      "lect": "Сергиенко Ольга Ивановна"
    },
    {
      "begin": "17:30",
      "end": "18:50",
      "week": 0,
      "place": "1122а ул.Ломоносова, д.9, лит.М",
      "subj": "Экологические риски и экологическое страхование(Лаб) :  с 1-9 нед.",
      "lect": "Сергиенко Ольга Ивановна"
    }
  ]
}
